inventronet/__init__.py
inventronet/activations/__init__.py
inventronet/activations/activation.py
inventronet/activations/leaky_relu.py
inventronet/activations/linear.py
inventronet/activations/relu.py
inventronet/activations/sigmoid.py
inventronet/activations/softmax.py
inventronet/activations/tanh.py
inventronet/layers/__init__.py
inventronet/layers/batch_normalization.py
inventronet/layers/dense.py
inventronet/layers/dropout.py
inventronet/layers/layer.py
inventronet/layers/shape_error.py
inventronet/losses/__init__.py
inventronet/losses/binary_cross_entropy.py
inventronet/losses/categorical_cross_entropy.py
inventronet/losses/loss.py
inventronet/losses/mean_absolute_error.py
inventronet/losses/mean_squared_error.py
inventronet/metrics/__init__.py
inventronet/metrics/accuracy.py
inventronet/metrics/metric.py
inventronet/metrics/precision.py
inventronet/models/__init__.py
inventronet/models/model.py
inventronet/models/sequential.py
inventronet/optimizers/__init__.py
inventronet/optimizers/adam.py
inventronet/optimizers/optimizer.py
inventronet/optimizers/stochastic_gradient_descent.py
inventronet/preprocessing/__init__.py
inventronet/preprocessing/count_vectorizer.py
inventronet/preprocessing/data_split.py
tests/__init__.py
tests/activations/__init__.py
tests/activations/test_leaky_relu.py
tests/activations/test_linear.py
tests/activations/test_relu.py
tests/activations/test_sigmoid.py
tests/activations/test_softmax.py
tests/activations/test_tanh.py
tests/layers/__init__.py
tests/layers/conftest.py
tests/layers/test_batch_normalization.py
tests/layers/test_dense.py
tests/layers/test_dropout.py
tests/losses/__init__.py
tests/losses/test_binary_cross_entropy.py
tests/losses/test_categorical_cross_entropy.py
tests/losses/test_mean_absolute_error.py
tests/losses/test_mean_squared_error.py
tests/metrics/__init__.py
tests/metrics/test_accuracy.py
tests/metrics/test_precision.py
tests/models/__init__.py
tests/models/test_sequential.py
tests/optimizers/__init__.py
inventronet-0.0.8a0.dist-info/LICENSE
inventronet-0.0.8a0.dist-info/METADATA
inventronet-0.0.8a0.dist-info/WHEEL
inventronet-0.0.8a0.dist-info/top_level.txt
inventronet-0.0.8a0.dist-info/RECORD
